wagtail_spa/__init__.py
wagtail_spa/apps.py
wagtail_spa/settings.py
wagtail_spa/urls.py
wagtail_spa/views.py
wagtail_spa_routing-0.1.1.dist-info/METADATA
wagtail_spa_routing-0.1.1.dist-info/WHEEL
wagtail_spa_routing-0.1.1.dist-info/top_level.txt
wagtail_spa_routing-0.1.1.dist-info/RECORD
