Metadata-Version: 2.1
Name: wagtail-spa-routing
Version: 0.1.1
Summary: Wagtail SPA routing tools
Home-page: https://github.com/jetstyle/wagtail-spa-routing
Author: Anton Vakhmin
Author-email: html.ru@gmail.com
License: MIT
Platform: UNKNOWN
Classifier: License :: OSI Approved :: MIT License
Classifier: Programming Language :: Python :: 3
Classifier: Programming Language :: Python :: 3.7
Requires-Dist: django
Requires-Dist: wagtail
Requires-Dist: djangorestframework
